gff_to_genbank/__about__.py
gff_to_genbank/__init__.py
gff_to_genbank/gff_to_genbank.py
gff_to_genbank-0.1.0.dist-info/METADATA
gff_to_genbank-0.1.0.dist-info/WHEEL
gff_to_genbank-0.1.0.dist-info/entry_points.txt
gff_to_genbank-0.1.0.dist-info/licenses/LICENSE.txt
gff_to_genbank-0.1.0.dist-info/RECORD
