Metadata-Version: 2.3
Name: gff-to-genbank
Version: 0.1.0
Summary: Script to convert from GFF to Genbank
Project-URL: Documentation, https://github.com/corneliusroemer/gff-to-genbank#readme
Project-URL: Issues, https://github.com/corneliusroemer/gff-to-genbank/issues
Project-URL: Source, https://github.com/corneliusroemer/gff-to-genbank
Author-email: Cornelius Roemer <cornelius.roemer@gmail.com>
License-Expression: MIT
License-File: LICENSE.txt
Classifier: Development Status :: 4 - Beta
Classifier: Programming Language :: Python
Classifier: Programming Language :: Python :: 3.8
Classifier: Programming Language :: Python :: 3.9
Classifier: Programming Language :: Python :: 3.10
Classifier: Programming Language :: Python :: 3.11
Classifier: Programming Language :: Python :: 3.12
Classifier: Programming Language :: Python :: Implementation :: CPython
Classifier: Programming Language :: Python :: Implementation :: PyPy
Requires-Python: >=3.8
Requires-Dist: bcbio-gff>=0.7
Requires-Dist: biopython>=1.81
